progresstrangebar/__init__.py
progresstrangebar/bar.py
progresstrangebar-0.1.0.dist-info/METADATA
progresstrangebar-0.1.0.dist-info/WHEEL
progresstrangebar-0.1.0.dist-info/top_level.txt
progresstrangebar-0.1.0.dist-info/RECORD
