Metadata-Version: 2.4
Name: progresstrangebar
Version: 0.1.0
Summary: For tqdm edited and selected.
Author-email: 刘浩天 <minecraftcaldson@outlook.com>
Requires-Python: >=3.9
